[
  {
    "topic": "immigration",
    "party": "Liberal",
    "year": 2025,
    "title": {
      "EN": "Cap immigration temporarily"
    },
    "references": [
      {
        "date": "2025-02-24",
        "title": "Liberal leadership hopeful Mark Carney says he would put a temporary cap on immigration",
        "publisher": "The Globe and Mail",
        "url": "https://www.theglobeandmail.com/canada/article-liberal-leadership-hopeful-mark-carney-says-he-would-put-a-temporary/"
      }
    ],
    "id": 1
  },
  {
    "topic": "immigration",
    "party": "Conservative",
    "year": 2025,
    "title": {
      "EN": "Hire more border agents"
    },
    "references": [
      {
        "date": "2025-03-04",
        "title": "Border officer union cites staffing shortfalls as Trump proceeds with tariff threats",
        "publisher": "The Star",
        "url": "https://www.thestar.com/politics/federal/border-officer-union-cites-staffing-shortfalls-as-trump-proceeds-with-tariff-threats/article_4afb852e-69de-5e4a-9efe-680e24a49d54.html"
      }
    ],
    "id": 2
  },
  {
    "topic": "immigration",
    "party": "Conservative",
    "year": 2025,
    "title": {
      "EN": "Reduce annual permanent resident intake"
    },
    "references": [
      {
        "date": "2024",
        "title": "EXCLUSIVE: Poilievre suggests capping immigration at Harper-era levels, deportations for wrongdoers",
        "publisher": "Juno News",
        "url": "https://www.junonews.com/p/exclusive-poilievre-vows-200k-250k"
      }
    ],
    "id": 3
  },
  {
    "topic": "international-trade",
    "party": "Conservative",
    "year": 2025,
    "title": {
      "EN": "Dollar-for-dollar retaliatory tariffs"
    },
    "references": [
      {
        "date": "2025-03-11",
        "title": "Trump placing 25% tariff on steel, aluminum after backing off 50% threat",
        "publisher": "CBC News",
        "url": "https://www.cbc.ca/news/politics/trump-canada-steel-alumimum-tariffs-1.7480309"
      },
      {
        "date": "2025-03-11",
        "title": "Donald Trump hints at reversing latest 50 per cent tariff threat on Canadian metals, Doug Ford lines up Washington meeting in signs of potential breakthrough ",
        "publisher": "The Star",
        "url": "https://www.thestar.com/politics/federal/donald-trump-hints-at-tariff-reversal-after-ontario-suspends-electricity-surcharge/article_6af4e772-fe83-11ef-9a6b-83ab47d11c5a.html"
      },
      {
        "date": "2025-03-11",
        "title": "Trump tariffs and Canada: 25% levy on steel and aluminum will go into effect tomorrow; Doug Ford agrees to suspend electricity tax ",
        "publisher": "The Star",
        "url": "https://www.thestar.com/politics/federal/trump-tariffs-canada/article_fbd77efe-fe87-11ef-aff6-6bf80c3baf29.html"
      },
      {
        "date": "2025-03-11",
        "title": "Poilievre wants to impose 50 per cent metal tariffs on U.S. after latest Trump threat",
        "publisher": "The Star",
        "url": "https://www.thestar.com/politics/federal/poilievre-wants-to-impose-50-per-cent-metal-tariffs-on-u-s-after-latest-trump/article_f32139b7-fff6-52a0-bce9-92b0ed6cea88.html"
      }
    ],
    "id": 4
  },
  {
    "topic": "international-trade",
    "party": "NDP",
    "year": 2025,
    "title": {
      "EN": "Dollar-for-dollar retaliatory tariffs"
    },
    "references": [
      {
        "date": "2025-03-12",
        "title": "Carney transition team met with PMO staff Tuesday, hope for PM swearing-in by Friday",
        "publisher": "CBC News",
        "url": "https://www.cbc.ca/news/politics/jagmeet-singh-reacts-trumps-tariffs-canadian-steel-and-aluminum-1.7481228"
      },
      {
        "date": "2025-03-12",
        "title": "Trump Tariffs and Canada: U.S. tariffs on steel, aluminum in effect; Canada’s retaliatory levies start Thursday; Carney to become PM Friday",
        "publisher": "The Star",
        "url": "https://www.thestar.com/politics/federal/trump-tariffs-canada-live/article_280d0976-feb5-11ef-94ab-a393bb21ba46.html"
      }
    ],
    "id": 5
  },
  {
    "topic": "international-trade",
    "party": "Bloc",
    "year": 2025,
    "title": {
      "EN": "Protect supply management"
    },
    "references": [
      {
        "date": "2025-03-14",
        "title": "Crise tarifaire et négociations à venir de l’ACEUM : Pas question d’abandonner la gestion de l’offre",
        "publisher": "Bloc Québécois",
        "url": "https://www.blocquebecois.org/crise-tarifaire-et-negociations-a-venir-de-laceum-pas-question-dabandonner-la-gestion-de-loffre/"
      }
    ],
    "id": 6
  },
  {
    "topic": "international-trade",
    "party": "Liberal",
    "year": 2025,
    "title": {
      "EN": "Diversify trade relationships"
    },
    "references": [
      {
        "date": "2025-03-14",
        "title": "Who are the new faces in Carney's cabinet? Who's on their way out?",
        "publisher": "CBC News",
        "url": "https://www.cbc.ca/news/politics/who-is-in-mark-carney-cabinet-1.7484013"
      },
      {
        "date": "2025-03-14",
        "title": "Joly tells Marco Rubio 'Canada's sovereignty is not up to debate, period'",
        "publisher": "CBC News",
        "url": "https://www.cbc.ca/news/politics/g7-canada-joly-tells-rubio-hands-off-1.7483573"
      }
    ],
    "id": 7
  },
  {
    "topic": "government",
    "party": "Conservative",
    "year": 2025,
    "title": {
      "EN": "Conflict of Interest Act reform"
    },
    "references": [
      {
        "date": "2025-03-11",
        "title": "Poilievre says Carney's taking advantage of an ethics loophole. Is he right?",
        "publisher": "CBC News",
        "url": "https://www.cbc.ca/news/politics/mark-carney-puts-assets-in-blind-trust-1.7480909?cmp=rss"
      },
      {
        "date": "2025-03-14",
        "title": "Incoming prime minister Mark Carney says he has put his assets in a blind trust",
        "publisher": "The Star",
        "url": "https://www.thestar.com/politics/federal/incoming-prime-minister-mark-carney-says-he-has-put-his-assets-in-a-blind-trust/article_930e6cc2-ac45-5e94-921e-b92eb095e26c.html"
      }
    ],
    "id": 8
  },
  {
    "topic": "government",
    "party": "Green",
    "year": 2025,
    "title": {
      "EN": "“Wartime” cabinet focused on responding to U.S. threats"
    },
    "references": [
      {
        "date": "March 11, 2025",
        "title": "Poilievre wants to impose 50 per cent metal tariffs on U.S. after latest Trump threat",
        "url": "https://www.thestar.com/politics/federal/poilievre-wants-to-impose-50-per-cent-metal-tariffs-on-u-s-after-latest-trump/article_f32139b7-fff6-52a0-bce9-92b0ed6cea88.html"
      }
    ],
    "id": 9
  },
  {
    "topic": "government",
    "party": "Bloc",
    "year": 2025,
    "title": {
      "EN": "More safeguards around foreign interference"
    },
    "references": [
      {
        "date": "2025-01-28",
        "title": "Rapport de la Commission Hogue : Il faut rebâtir la confiance",
        "publisher": "Bloc Québécois",
        "url": "https://www.blocquebecois.org/rapport-de-la-commission-hogue-il-faut-rebatir-la-confiance/"
      }
    ],
    "id": 10
  },
  {
    "topic": "indigenous-relations",
    "party": "Bloc",
    "year": 2025,
    "title": {
      "EN": "Cancel Chalk River project"
    },
    "references": [
      {
        "date": "2025-02-21",
        "title": "Victoire en Cour de la Première Nation de Kebaowek: Ottawa doit écouter et renoncer à Chalk River",
        "publisher": "Bloc Québécois",
        "url": "https://www.blocquebecois.org/victoire-en-cour-de-la-premiere-nation-de-kebaowek-ottawa-doit-ecouter-et-renoncer-a-chalk-river/"
      }
    ],
    "id": 11
  },
  {
    "topic": "affordability",
    "party": "NDP",
    "year": 2025,
    "title": {
      "EN": "Grocery price cap"
    },
    "references": [
      {
        "date": "2025-02-11",
        "title": "Reality Check – Chrystia Freeland Flip-Flops on Grocery Price Cap",
        "publisher": "NDP",
        "url": "https://www.ndp.ca/news/reality-check-chrystia-freeland-flip-flops-grocery-price-cap"
      }
    ],
    "id": 13
  },
  {
    "topic": "civil-rights",
    "party": "NDP",
    "year": 2025,
    "title": {
      "EN": "Investigate X for privacy concerns"
    },
    "references": [
      {
        "date": "2025-02-25",
        "title": "NDP’s Masse urges investigation into X regarding data privacy concerns",
        "publisher": "NDP Official Website",
        "url": "https://www.ndp.ca/news/ndps-masse-urges-investigation-x-regarding-data-privacy-concerns"
      }
    ],
    "id": 14
  },
  {
    "topic": "civil-rights",
    "party": "NDP",
    "year": 2025,
    "title": {
      "EN": "Support workers' right to strike"
    },
    "references": [
      {
        "date": "2025-02-20",
        "title": "Jagmeet Singh denounces the CAQ's frontal attack on workers' rights",
        "publisher": "NDP Official Website",
        "url": "https://www.ndp.ca/news/jagmeet-singh-denounces-caqs-frontal-attack-workers-rights"
      }
    ],
    "id": 15
  },
  {
    "topic": "civil-rights",
    "party": "NDP",
    "year": 2025,
    "title": {
      "EN": "Expand CBSA training centre in Windsor"
    },
    "references": [
      {
        "date": "2025-02-10",
        "title": "NDP will build CBSA training centre in Windsor",
        "publisher": "NDP Official Website",
        "url": "https://www.ndp.ca/news/ndp-will-build-cbsa-training-centre-windsor"
      }
    ],
    "id": 16
  },
  {
    "topic": "civil-rights",
    "party": "Bloc",
    "year": 2025,
    "title": {
      "EN": "Redirect anglicization funding"
    },
    "references": [
      {
        "date": "2025-02-27",
        "title": "Analyse des comptes publics 2023-2024: 200 millions pour l’anglicisation au Québec",
        "publisher": "Bloc Québécois Official Website",
        "url": "https://www.blocquebecois.org/?p=30239"
      }
    ],
    "id": 17
  },
  {
    "topic": "health-and-safety",
    "party": "NDP",
    "year": 2025,
    "title": {
      "EN": "Ban corporate healthcare billing"
    },
    "references": [
      {
        "date": "February 24th, 2025",
        "title": "NDP commits to stop corporations from billing patients for care",
        "publisher": "NDP.ca",
        "url": "https://www.ndp.ca/news/ndp-commits-stop-corporations-billing-patients-care"
      }
    ],
    "id": 18
  },
  {
    "topic": "health-and-safety",
    "party": "NDP",
    "year": 2025,
    "title": {
      "EN": "Support abortion access"
    },
    "references": [
      {
        "date": "March 8, 2025",
        "title": "NDP statement on International Women’s Day 2025",
        "publisher": "NDP.ca",
        "url": "https://www.ndp.ca/news/ndp-statement-international-womens-day-2025"
      }
    ],
    "id": 19
  },
  {
    "topic": "health-and-safety",
    "party": "Conservative",
    "year": 2025,
    "title": {
      "EN": "Ban hard drugs, end decriminalization"
    },
    "references": [
      {
        "date": "2024-04-05",
        "title": "Poilievre Interviews with Comox Valley Record During Tour in Courtenay",
        "publisher": "Comox Valley Record",
        "url": "https://www.comoxvalleyrecord.com/local-news/poilievre-interviews-with-comox-valley-record-during-tour-in-courtenay-7338532"
      }
    ],
    "id": 20
  },
  {
    "topic": "housing",
    "party": "Liberal",
    "year": 2025,
    "title": {
      "EN": "Double housing construction"
    },
    "references": [
      {
        "date": "2025-02-24",
        "title": "Liberal leadership hopeful Mark Carney says he would put a temporary cap on immigration",
        "publisher": "The Globe and Mail",
        "url": "https://www.theglobeandmail.com/canada/article-liberal-leadership-hopeful-mark-carney-says-he-would-put-a-temporary/"
      }
    ],
    "id": 21
  },
  {
    "topic": "housing",
    "party": "Conservative",
    "year": 2025,
    "title": {
      "EN": "Eliminate GST on new homes"
    },
    "references": [
      {
        "date": "2025-03-14",
        "title": "Mark Carney’s Fourth Liberal Term Will Be Just Like Justin’s",
        "publisher": "Conservative Party of Canada",
        "url": "https://www.conservative.ca/mark-carneys-fourth-liberal-term-will-be-just-like-justins/#utm_source=rss&utm_medium=rss&utm_campaign=mark-carneys-fourth-liberal-term-will-be-just-like-justins"
      }
    ],
    "id": 23
  },
  {
    "topic": "housing",
    "party": "Conservative",
    "year": 2025,
    "title": {
      "EN": "Incentives for municipal housing"
    },
    "references": [
      {
        "date": "2025-03-14",
        "title": "Mark Carney’s Fourth Liberal Term Will Be Just Like Justin’s",
        "publisher": "Conservative Party of Canada",
        "url": "https://www.conservative.ca/mark-carneys-fourth-liberal-term-will-be-just-like-justins/#utm_source=rss&utm_medium=rss&utm_campaign=mark-carneys-fourth-liberal-term-will-be-just-like-justins"
      }
    ],
    "id": 24
  },
  {
    "topic": "housing",
    "party": "NDP",
    "year": 2025,
    "title": {
      "EN": "Invest in affordable housing"
    },
    "references": [
      {
        "date": "February 19th, 2025",
        "title": "The NDP says it's time to invest more in affordable, social and community housing",
        "publisher": "NDP.ca",
        "url": "https://www.ndp.ca/news/ndp-says-its-time-invest-more-affordable-social-and-community-housing"
      }
    ],
    "id": 25
  },
  {
    "topic": "housing",
    "party": "Bloc",
    "year": 2025,
    "title": {
      "EN": "Unconditional housing funds transfer"
    },
    "references": [
      {
        "date": "2025-01-30",
        "title": "Fonds canadien pour les infrastructures liées au logement : Ottawa doit cesser de faire obstacle au logement",
        "publisher": "Bloc Québécois",
        "url": "https://www.blocquebecois.org/fonds-canadien-pour-les-infrastructures-liees-au-logement-ottawa-doit-cesser-de-faire-obstacle-au-logement/"
      }
    ],
    "id": 26
  },
  {
    "topic": "social-assistance",
    "party": "Bloc",
    "year": 2025,
    "title": {
      "EN": "Equitable pension system"
    },
    "references": [
      {
        "date": "2025-03-13",
        "title": "Circonscription de Côte-du-Sud—Rivière-du-Loup—Kataskomiq—Témiscouata : Diane Sénécal investie candidate du Bloc Québécois",
        "publisher": "Bloc Québécois",
        "url": "https://www.blocquebecois.org/circonscription-de-cote-du-sud-riviere-du-loup-kataskomiq-temiscouata-diane-senecal-investie-candidate-du-bloc-quebecois/"
      }
    ],
    "id": 28
  },
  {
    "topic": "social-assistance",
    "party": "NDP",
    "year": 2025,
    "title": {
      "EN": "Support Canada Disability Benefit"
    },
    "references": [
      {
        "date": "2025-03-03",
        "title": "NDP welcomes long-awaited rollout of the Canada Disability Benefit",
        "publisher": "NDP.ca",
        "url": "https://www.ndp.ca/news/ndp-welcomes-long-awaited-rollout-canada-disability-benefit"
      }
    ],
    "id": 29
  },
  {
    "topic": "social-assistance",
    "party": "NDP",
    "year": 2025,
    "title": {
      "EN": "Increase employment insurance payments for tariff-affected workers"
    },
    "references": [
      {
        "date": "2025-03-09",
        "title": "Trouble awaits the next Liberal leader. Here’s what they’ll be up against — and when they could face an election",
        "publisher": "The Star",
        "url": "https://www.thestar.com/politics/federal/trouble-awaits-the-next-liberal-leader-heres-what-theyll-be-up-against-and-when-they/article_294da3a8-fa9c-11ef-9883-abfa223c53c5.html"
      }
    ],
    "id": 30
  },
  {
    "topic": "arts-and-culture",
    "party": "NDP",
    "year": 2025,
    "title": {
      "EN": "Invest in Canadian journalism"
    },
    "references": [
      {
        "date": "2025-02-20",
        "title": "Jagmeet Singh and the NDP will invest in Canadian journalism and CBC/Radio-Canada",
        "publisher": "NDP",
        "url": "https://www.ndp.ca/news/jagmeet-singh-and-ndp-will-invest-canadian-journalism-and-cbcradio-canada"
      }
    ],
    "id": 31
  },
  {
    "topic": "arts-and-culture",
    "party": "Liberal",
    "year": 2025,
    "title": {
      "EN": "New ministry for Canadian Culture"
    },
    "references": [
      {
        "date": "2025-03-14",
        "title": "A rival left out, big GTA presence: 4 takeaways from Mark Carney’s cabinet",
        "publisher": "The Star",
        "url": "https://www.thestar.com/politics/federal/a-rival-left-out-big-gta-presence-4-takeaways-from-mark-carneys-cabinet/article_db6ab1d6-010c-11f0-8250-e7d68a0c54bc.html"
      },
      {
        "date": "2025-03-14",
        "title": "Five things to know about Prime Minister Mark Carney’s new cabinet",
        "publisher": "The Star",
        "url": "https://www.thestar.com/politics/federal/five-things-to-know-about-prime-minister-mark-carneys-new-cabinet/article_65633a69-6595-51f6-a6b5-0bea0951f474.html"
      }
    ],
    "id": 32
  },
  {
    "topic": "youth_child-care",
    "party": "NDP",
    "year": 2025,
    "title": {
      "EN": "Better wages for childcare workers"
    },
    "references": [
      {
        "date": "March 6th, 2025",
        "title": "NDP wants to see better wages for child care workers, creating more spots for kids",
        "publisher": "NDP",
        "url": "https://www.ndp.ca/news/ndp-wants-see-better-wages-child-care-workers-creating-more-spots-kids"
      }
    ],
    "id": 33
  },
  {
    "topic": "infrastructure",
    "party": "NDP",
    "year": 2025,
    "title": {
      "EN": "Use Canadian steel for infrastructure"
    },
    "references": [
      {
        "date": "February 19th, 2025",
        "title": "High speed rail must be built publicly, using Canadian steel and aluminum: NDP",
        "publisher": "NDP Official Website",
        "url": "https://www.ndp.ca/news/high-speed-rail-must-be-built-publicly-using-canadian-steel-and-aluminum-ndp"
      }
    ],
    "id": 34
  },
  {
    "topic": "infrastructure",
    "party": "NDP",
    "year": 2025,
    "title": {
      "EN": "Prioritize Canadian companies for infrastructure"
    },
    "references": [
      {
        "date": "February 20, 2025",
        "title": "Singh takes Carney to task on service cuts for people, tax cut for the ultra-wealthy in speech to unions",
        "publisher": "NDP Official Website",
        "url": "https://www.ndp.ca/news/singh-takes-carney-task-service-cuts-people-tax-cut-ultra-wealthy-speech-unions"
      },
      {
        "date": "February 18, 2025",
        "title": "Canadian builds with Canadian steel: Singh lays out plan to build, not cut",
        "publisher": "NDP Official Website",
        "url": "https://www.ndp.ca/news/canadian-builds-canadian-steel-singh-lays-out-plan-build-not-cut"
      }
    ],
    "id": 35
  },
  {
    "topic": "infrastructure",
    "party": "Conservative",
    "year": 2025,
    "title": {
      "EN": "Repeal Bill C-69 for resource development"
    },
    "references": [
      {
        "date": "March 14, 2025",
        "title": "Mark Carney’s Fourth Liberal Term Will Be Just Like Justin’s",
        "publisher": "Conservative Party of Canada",
        "url": "https://www.conservative.ca/mark-carneys-fourth-liberal-term-will-be-just-like-justins/#utm_source=rss&utm_medium=rss&utm_campaign=mark-carneys-fourth-liberal-term-will-be-just-like-justins"
      },
      {
        "date": "March 10, 2025",
        "title": "Mark Carney Will Sell Out Canadians",
        "publisher": "Conservative Party of Canada",
        "url": "https://www.conservative.ca/mark-carney-will-sell-out-canadians/#utm_source=rss&utm_medium=rss&utm_campaign=mark-carney-will-sell-out-canadians"
      }
    ],
    "id": 36
  },
  {
    "topic": "infrastructure",
    "party": "Bloc",
    "year": 2025,
    "title": {
      "EN": "Support high-speed rail project"
    },
    "references": [
      {
        "date": "February 19, 2025",
        "title": "Projet de train à grande vitesse : Un pas dans la bonne direction",
        "publisher": "Bloc Québécois Official Website",
        "url": "https://www.blocquebecois.org/projet-de-train-a-grande-vitesse-un-pas-dans-la-bonne-direction/"
      }
    ],
    "id": 37
  },
  {
    "topic": "infrastructure",
    "party": "Liberal",
    "year": 2025,
    "title": {
      "EN": "Award icebreaker contracts to Canadian shipyards"
    },
    "references": [
      {
        "date": "March 8, 2025",
        "title": "Ottawa announces 2nd domestic contract for polar icebreaker",
        "publisher": "The Star",
        "url": "https://www.thestar.com/politics/federal/ottawa-announces-2nd-domestic-contract-for-polar-icebreaker/article_8ebaa00d-a617-5af5-b4f3-7df4548af8c5.html"
      }
    ],
    "id": 38
  },
  {
    "topic": "infrastructure",
    "party": "NDP",
    "year": 2025,
    "title": {
      "EN": "Build east-west energy grid"
    },
    "references": [
      {
        "date": "March 10, 2025",
        "title": "NDP Workers for Canada plan to support B.C. jobs and workers",
        "publisher": "NDP Official Website",
        "url": "https://www.ndp.ca/news/ndp-workers-canada-plan-support-bc-jobs-and-workers"
      }
    ],
    "id": 39
  },
  {
    "topic": "foreign-policy",
    "party": "NDP",
    "year": 2025,
    "title": {
      "EN": "Canadian peacekeeping force"
    },
    "references": [
      {
        "date": "February 14th, 2025",
        "title": "NDP Statement on Canada’s withdrawal from the UN Mission in the Democratic Republic of Congo",
        "publisher": "NDP",
        "url": "https://www.ndp.ca/news/ndp-statement-canadas-withdrawal-un-mission-democratic-republic-congo"
      }
    ],
    "id": 40
  },
  {
    "topic": "foreign-policy",
    "party": "Conservative",
    "year": 2025,
    "title": {
      "EN": "Arctic military base, naval icebreakers"
    },
    "references": [
      {
        "date": "February 10th, 2025",
        "title": "Poilievre pledges Arctic military base, naval icebreakers if party forms government",
        "publisher": "The Globe and Mail",
        "url": "https://www.theglobeandmail.com/canada/article-poilievre-pledges-arctic-military-base-naval-icebreakers-if-party/"
      }
    ],
    "id": 42
  },
  {
    "topic": "foreign-policy",
    "party": "Liberal",
    "year": 2025,
    "title": {
      "EN": "Meet NATO spending target by 2030"
    },
    "references": [
      {
        "date": "March 12th, 2025",
        "title": "Carney transition team met with PMO staff Tuesday, hope for PM swearing-in by Friday",
        "publisher": "CBC News",
        "url": "https://www.cbc.ca/news/politics/carney-transition-team-met-pmo-staff-1.7481228?cmp=rss"
      },
      {
        "date": "March 18th, 2025",
        "title": "Mark Carney says Canada will buy $6-billion missile detection system to confront threats from Russia and China",
        "publisher": "The Star",
        "url": "https://www.thestar.com/politics/federal/mark-carney-says-canada-will-buy-6-billion-missile-detection-system-to-confront-threats-from/article_0ad77652-040f-11f0-9fcd-9f1a2cf539b2.html"
      }
    ],
    "id": 43
  },
  {
    "topic": "foreign-policy",
    "party": "Liberal",
    "year": 2025,
    "title": {
      "EN": "Modernize NORAD"
    },
    "references": [
      {
        "date": "March 12th, 2025",
        "title": "Carney transition team met with PMO staff Tuesday, hope for PM swearing-in by Friday",
        "publisher": "CBC News",
        "url": "https://www.cbc.ca/news/politics/carney-transition-team-met-pmo-staff-1.7481228?cmp=rss"
      }
    ],
    "id": 44
  },
  {
    "topic": "foreign-policy",
    "party": "Liberal",
    "year": 2025,
    "title": {
      "EN": "Reconsider purchase of F-35 fighter jets from USA"
    },
    "references": [
      {
        "date": "March 14th, 2025",
        "title": "Canada reconsidering F-35 purchase amid tensions with Washington, says minister",
        "publisher": "CBC News",
        "url": "https://www.cbc.ca/news/politics/f35-blair-trump-1.7484477?cmp=rss"
      },
      {
        "date": "March 19, 2025",
        "title": "Canada must weigh risk Trump blocks software upgrades for F-35s: former official",
        "publisher": "The Globe and Mail",
        "url": "https://www.theglobeandmail.com/politics/article-canada-must-weigh-risk-trump-blocks-software-upgrades-for-f-35s/"
      },
      {
        "date": "2025-03-18",
        "title": "Carney announces plans to boost Canada's military footprint in the Arctic",
        "publisher": "The Star",
        "url": "https://www.thestar.com/politics/federal/carney-announces-plans-to-boost-canadas-military-footprint-in-the-arctic/article_c4b24e52-3f0e-54f6-89a7-1241f062e9ed.html"
      },
      {
        "date": "2025-03-18",
        "title": "Mark Carney says Canada will buy $6 billion missile detection system to confront threats from Russia, China",
        "publisher": "The Star",
        "url": "https://www.thestar.com/politics/federal/mark-carney-says-canada-will-buy-6-billion-missile-detection-system-to-confront-threats-from/article_0ad77652-040f-11f0-9fcd-9f1a2cf539b2.html"
      },
      {
        "date": "2025-03-18",
        "title": "Mark Carney says Canada will review F-35 fighter jet contract",
        "publisher": "The Star",
        "url": "https://www.thestar.com/politics/federal/mark-carney-says-canada-will-buy-6-billion-missile-detection-system-to-confront-threats-from/article_0ad77652-040f-11f0-9fcd-9f1a2cf539b2.html"
      }
    ],
    "id": 45
  },
  {
    "topic": "foreign-policy",
    "party": "Bloc",
    "year": 2025,
    "title": {
      "EN": "Sanctions against Rwanda"
    },
    "references": [
      {
        "date": "February 21st, 2025",
        "title": "Le Bloc Québécois condamne les opérations du Rwanda en République démocratique du Congo",
        "publisher": "Bloc Québécois",
        "url": "https://www.blocquebecois.org/le-bloc-quebecois-condamne-les-operations-du-rwanda-en-republique-democratique-du-congo/"
      }
    ],
    "id": 46
  },
  {
    "topic": "foreign-policy",
    "party": "Bloc",
    "year": 2025,
    "title": {
      "EN": "Border security concerns"
    },
    "references": [
      {
        "date": "February 12th, 2025",
        "title": "Diminution des heures d’ouverture des postes frontaliers : Le ministre McGuinty doit revoir sa décision",
        "publisher": "Bloc Québécois",
        "url": "https://www.blocquebecois.org/?p=30186"
      }
    ],
    "id": 47
  },
  {
    "topic": "foreign-policy",
    "party": "Bloc",
    "year": 2025,
    "title": {
      "EN": "Oppose english promotion"
    },
    "references": [
      {
        "date": "February 27th, 2025",
        "title": "Analyse des comptes publics 2023-2024: 200 millions pour l’anglicisation au Québec",
        "publisher": "Bloc Québécois",
        "url": "https://www.blocquebecois.org/analyse-des-comptes-publics-2023-2024-200-millions-pour-langlicisation-au-quebec/"
      }
    ],
    "id": 48
  },
  {
    "topic": "infrastructure",
    "party": "Liberal",
    "year": 2025,
    "title": {
      "EN": "Modernize ports and rail for new trade corridors"
    },
    "references": [
      {
        "date": "February 20th, 2025",
        "title": "Carney shifts carbon price strategy, pledges to make Canada a clean energy superpower",
        "publisher": "CBC News",
        "url": "https://www.nationalobserver.com/2025/02/20/news/carney-carbon-tax-clean-energy-superpower"
      }
    ],
    "id": 49
  },
  {
    "topic": "foreign-policy",
    "party": "Conservative",
    "year": 2025,
    "title": {
      "EN": "Commit $1B to co-fund roads, approve “Ring of Fire” northern Ontario mining permits within 6 months"
    },
    "references": [
      {
        "date": "2023",
        "title": "Poilievre promises to unlock Ring of Fire",
        "publisher": "Conservative Party of Canada",
        "url": "https://www.conservative.ca/poilievre-promises-to-unlock-ring-of-fire/#utm_source=rss&utm_medium=rss&utm_campaign=poilievre-promises-to-unlock-ring-of-fire"
      },
      {
        "date": "2025-03-19",
        "title": "Pierre Poilievre says he wants to greenlight Ring of Fire mining permits within six months",
        "publisher": "The Star",
        "url": "https://www.thestar.com/politics/federal/poilievre-says-he-wants-to-greenlight-ring-of-fire-mining-permits-within-six-months/article_9b66819e-8fe0-56b7-a984-b5239a8cdf7f.html"
      },
      {
        "date": "2025-03-19",
        "title": "Federal Conservative leader stops in Sudbury with promises of 'unlocking' Ring of Fire",
        "publisher": "CBC News",
        "url": "https://www.cbc.ca/news/canada/sudbury/ring-of-fire-poiliever-critical-minerals-sudbury-1.7487363?cmp=rss"
      },
      {
        "date": "2025-03-19",
        "title": "Poilievre says Conservatives would co-fund roads with Ontario into Ring of Fire, speed up development",
        "publisher": "The Globe and Mail",
        "url": "https://www.theglobeandmail.com/business/article-poilievre-says-conservatives-would-co-fund-roads-with-ontario-into/"
      }
    ],
    "id": 50
  },
  {
    "topic": "foreign-policy",
    "party": "Liberal",
    "year": 2025,
    "title": {
      "EN": "Purchase $6 billion missile detection system"
    },
    "references": [
      {
        "date": "2025-03-18",
        "title": "Canada will buy $6 billion missile detection system to confront threats from Russia, China",
        "publisher": "The Star",
        "url": "https://www.thestar.com/politics/federal/mark-carney-says-canada-will-buy-6-billion-missile-detection-system-to-confront-threats-from/article_0ad77652-040f-11f0-9fcd-9f1a2cf539b2.html"
      },
      {
        "date": "2025-03-18",
        "title": "Carney announces plans to boost Canada's military footprint in the Arctic",
        "publisher": "The Star",
        "url": "https://www.thestar.com/politics/federal/carney-announces-plans-to-boost-canadas-military-footprint-in-the-arctic/article_c4b24e52-3f0e-54f6-89a7-1241f062e9ed.html"
      },
      {
        "date": "2025-03-19",
        "title": "Canada will partner with Australia to build an Arctic Over-The-Horizon Radar system along the Canada-U.S. border into the Arctic, with an investment of more than $6 billion for this early warning detection system",
        "publisher": "CBC News",
        "url": "https://www.cbc.ca/news/canada/north/canada-early-warning-detection-arctic-1.7486640?cmp=rss"
      }
    ],
    "id": 51
  },
  {
    "topic": "foreign-policy",
    "party": "NDP",
    "year": 2025,
    "title": {
      "EN": "Cancel F-35 fighter jet contract with USA, build jets in Canada"
    },
    "references": [
      {
        "date": "2025-03-18",
        "title": "NDP says Liberal Arctic announcement ignores challenges facing Northerners",
        "publisher": "NDP",
        "url": "https://www.ndp.ca/news/ndp-says-liberal-arctic-announcement-ignores-challenges-facing-northerners-0"
      },
      {
        "date": "March 18, 2025",
        "title": "Mark Carney says Canada will buy $6-billion missile detection system to confront threats from Russia and China ",
        "publisher": "The Star",
        "url": "https://www.thestar.com/politics/federal/mark-carney-says-canada-will-buy-6-billion-missile-detection-system-to-confront-threats-from/article_0ad77652-040f-11f0-9fcd-9f1a2cf539b2.html"
      }
    ],
    "id": 52
  },
  {
    "topic": "environment",
    "party": "Conservative",
    "title": {
      "EN": "Eliminate industrial carbon tax"
    },
    "references": [
      {
        "date": "March 19, 2025",
        "title": "Energy CEOs write to federal political leaders on how to boost production, Canadian sovereignty",
        "publisher": "The Globe and Mail",
        "url": "https://www.theglobeandmail.com/politics/article-trade-war-federal-election-energy-ceos-letter/"
      },
      {
        "date": "March 19, 2025",
        "title": "Energy sector CEOs call on Ottawa to use emergency powers to speed up key projects ",
        "publisher": "The Star",
        "url": "https://www.thestar.com/politics/federal/energy-sector-ceos-call-on-ottawa-to-use-emergency-powers-to-speed-up-key-projects/article_42ec1db1-75df-5fc7-832b-8a2a4229759e.html"
      },
      {
        "date": "March 18, 2025",
        "title": "Alberta pioneered industrial carbon pricing. Now, Poilievre says he'd kill the federal mandate for it",
        "publisher": "CBC News",
        "url": "https://www.cbc.ca/news/canada/calgary/alberta-carbon-pricing-poilievre-kill-backstop-promise-reaction-1.7486111?cmp=rss"
      }
    ],
    "id": 53
  },
  {
    "topic": "government",
    "party": "NDP",
    "title": {
      "EN": "Reinstate dedicated Minister for Women and Gender Equality"
    },
    "references": [
      {
        "date": "March 19, 2025",
        "title": "NDP Women and Gender Equality Critic Leah Gazan calls out Prime Minister Carney for silencing women and gender diverse people",
        "publisher": "NDP Official Website",
        "url": "https://www.ndp.ca/news/ndp-women-and-gender-equality-critic-leah-gazan-calls-out-prime-minister-carney-silencing-women"
      }
    ],
    "id": 54
  },
  {
    "topic": "foreign-policy",
    "party": "NDP",
    "title": {
      "EN": "Meet NATO defense spending target by 2032"
    },
    "references": [
      {
        "date": "March 18, 2025",
        "title": "NDP says Liberal Arctic announcement ignores challenges facing Northerners",
        "publisher": "NDP Official Website",
        "url": "https://www.ndp.ca/news/ndp-says-liberal-arctic-announcement-ignores-challenges-facing-northerners-0"
      },
      {
        "date": "March 18, 2025",
        "title": "Mark Carney says Canada will buy $6-billion missile detection system to confront threats from Russia and China",
        "publisher": "The Star",
        "url": "https://www.thestar.com/politics/federal/mark-carney-says-canada-will-buy-6-billion-missile-detection-system-to-confront-threats-from/article_0ad77652-040f-11f0-9fcd-9f1a2cf539b2.html"
      }
    ],
    "id": 55
  },
  {
    "topic": "affordability",
    "party": "NDP",
    "title": {
      "EN": "Remove GST from essential items"
    },
    "references": [
      {
        "date": "March 18, 2025",
        "title": "Grocery price surge shows scrapping GST works to drive down prices",
        "publisher": "NDP Official Website",
        "url": "https://www.ndp.ca/news/grocery-price-surge-shows-scrapping-gst-works-drive-down-prices"
      }
    ],
    "id": 56
  },
  {
    "topic": "infrastructure",
    "party": "Liberal",
    "title": {
      "EN": "$253 million to fund housing and infrastructure supports in the north"
    },
    "references": [
      {
        "date": "March 18, 2025",
        "title": "Canada partners with Australia on radar system to detect threats from Russia and China",
        "publisher": "The Globe and Mail",
        "url": "https://www.theglobeandmail.com/politics/article-canada-australia-radar-system/"
      },
      {
        "date": "March 18, 2025",
        "title": "Mark Carney says Canada will buy $6-billion missile detection system to confront threats from Russia and China",
        "publisher": "The Star",
        "url": "https://www.thestar.com/politics/federal/mark-carney-says-canada-will-buy-6-billion-missile-detection-system-to-confront-threats-from/article_0ad77652-040f-11f0-9fcd-9f1a2cf539b2.html"
      },
      {
        "date": "March 18, 2025",
        "title": "Carney announces plans to boost Canada’s military footprint in the Arctic",
        "publisher": "The Star",
        "url": "https://www.thestar.com/politics/federal/carney-announces-plans-to-boost-canadas-military-footprint-in-the-arctic/article_c4b24e52-3f0e-54f6-89a7-1241f062e9ed.html"
      }
    ],
    "id": 57
  },
  {
    "topic": "infrastructure",
    "party": "NDP",
    "title": {
      "EN": "Invest in northern infrastructure"
    },
    "references": [
      {
        "date": "March 18, 2025",
        "title": "NDP will build jets in Canada, invest in Canada's North and Arctic sovereignty",
        "publisher": "NDP Official Website",
        "url": "https://www.ndp.ca/news/ndp-will-build-jets-canada-invest-canadas-north-and-arctic-sovereignty"
      }
    ],
    "id": 58
  },
  {
    "topic": "social-assistance",
    "party": "NDP",
    "title": {
      "EN": "Improve Employment Insurance for workers facing job loss"
    },
    "references": [
      {
        "date": "March 20, 2025",
        "title": "Jagmeet Singh calls for help for workers; Steelworkers back NDP ahead of election call",
        "publisher": "NDP Official Website",
        "url": "https://www.ndp.ca/news/jagmeet-singh-calls-help-workers-steelworkers-back-ndp-ahead-election-call"
      }
    ],
    "id": 60
  },
  {
    "topic": "international-trade",
    "party": "NDP",
    "title": {
      "EN": "Expand trade beyond the U.S. with higher standards for workers and the environment"
    },
    "references": [
      {
        "date": "March 20, 2025",
        "title": "Jagmeet Singh calls for help for workers; Steelworkers back NDP ahead of election call",
        "publisher": "NDP Official Website",
        "url": "https://www.ndp.ca/news/jagmeet-singh-calls-help-workers-steelworkers-back-ndp-ahead-election-call"
      }
    ],
    "id": 61
  },
  {
    "topic": "economy",
    "party": "NDP",
    "title": {
      "EN": "Prioritize procurement to buy and build Canadian"
    },
    "references": [
      {
        "date": "March 20, 2025",
        "title": "Jagmeet Singh calls for help for workers; Steelworkers back NDP ahead of election call",
        "publisher": "NDP Official Website",
        "url": "https://www.ndp.ca/news/jagmeet-singh-calls-help-workers-steelworkers-back-ndp-ahead-election-call"
      }
    ],
    "id": 62
  },
  {
    "topic": "economy",
    "party": "NDP",
    "title": {
      "EN": "Protect Canadian industries from foreign takeovers"
    },
    "references": [
      {
        "date": "March 20, 2025",
        "title": "Jagmeet Singh calls for help for workers; Steelworkers back NDP ahead of election call",
        "publisher": "NDP Official Website",
        "url": "https://www.ndp.ca/news/jagmeet-singh-calls-help-workers-steelworkers-back-ndp-ahead-election-call"
      }
    ],
    "id": 63
  },
  {
    "topic": "economy",
    "party": "NDP",
    "title": {
      "EN": "Increase capital spending on infrastructure"
    },
    "references": [
      {
        "date": "March 20, 2025",
        "title": "Jagmeet Singh calls for help for workers; Steelworkers back NDP ahead of election call",
        "publisher": "NDP Official Website",
        "url": "https://www.theglobeandmail.com/canada/article-manitoba-budget-offers-more-construction-spending-tax-changes/"
      }
    ],
    "id": 64
  },
  {
    "topic": "immigration",
    "party": "Liberal",
    "title": {
      "EN": "Continue reducing temporary resident numbers"
    },
    "references": [
      {
        "date": "March 20, 2025",
        "title": "New immigration minister says Trump presidency could prompt best and brightest to choose Canada",
        "publisher": "The Globe and Mail",
        "url": "https://www.theglobeandmail.com/politics/article-new-immigration-minister-says-trump-presidency-could-prompt-best-and/"
      }
    ],
    "id": 67
  },
  {
    "topic": "immigration",
    "party": "Liberal",
    "title": {
      "EN": "Consider changes to Safe Third Country Agreement with U.S."
    },
    "references": [
      {
        "date": "March 20, 2025",
        "title": "New immigration minister says Trump presidency could prompt best and brightest to choose Canada",
        "publisher": "The Globe and Mail",
        "url": "https://www.theglobeandmail.com/politics/article-new-immigration-minister-says-trump-presidency-could-prompt-best-and/"
      }
    ],
    "id": 68
  },
  {
    "topic": "infrastructure",
    "party": "Conservative",
    "title": {
      "EN": "Revive LNG project in Quebec's Saguenay region"
    },
    "references": [
      {
        "date": "March 20, 2025",
        "title": "Poilievre promotes reviving LNG project in Quebec’s Saguenay region",
        "publisher": "The Globe and Mail",
        "url": "https://www.theglobeandmail.com/politics/article-poilievre-promotes-reviving-lng-project-in-quebecs-saguenay-region/"
      }
    ],
    "id": 69
  },
  {
    "topic": "infrastructure",
    "party": "Conservative",
    "title": {
      "EN": "Create 'shovel-ready zones' for resource projects"
    },
    "references": [
      {
        "date": "March 20, 2025",
        "title": "Poilievre promotes reviving LNG project in Quebec’s Saguenay region",
        "publisher": "The Globe and Mail",
        "url": "https://www.theglobeandmail.com/politics/article-poilievre-promotes-reviving-lng-project-in-quebecs-saguenay-region/"
      },
      {
        "date": "March 20, 2025",
        "title": "Politics Insider: Lockheed Martin offers more local jobs if Ottawa will honour full F-35 contract",
        "publisher": "The Globe and Mail",
        "url": "https://www.theglobeandmail.com/politics/article-politics-insider-lockheed-martin-offers-more-local-jobs-if-ottawa-will/"
      }
    ],
    "id": 70
  },
  {
    "topic": "housing",
    "party": "Liberal",
    "title": {
      "EN": "Eliminate GST for first-time homebuyers on homes under $1M"
    },
    "references": [
      {
        "date": "March 20, 2025",
        "title": "Politics Insider: Lockheed Martin offers more local jobs if Ottawa will honour full F-35 contract",
        "publisher": "The Globe and Mail",
        "url": "https://www.theglobeandmail.com/politics/article-politics-insider-lockheed-martin-offers-more-local-jobs-if-ottawa-will/"
      }
    ],
    "id": 71
  },
  {
    "topic": "infrastructure",
    "party": "Liberal",
    "title": {
      "EN": "Speed up energy infrastructure project approvals"
    },
    "references": [
      {
        "date": "March 20, 2025",
        "title": "Carney pledges plan for faster development of new energy infrastructure",
        "publisher": "The Globe and Mail",
        "url": "https://www.theglobeandmail.com/politics/article-carney-pledges-plan-for-faster-development-of-new-energy/"
      }
    ],
    "id": 74
  },
  {
    "topic": "government",
    "party": "Bloc",
    "title": {
      "EN": "Oppose Translation Bureau workforce reduction"
    },
    "references": [
      {
        "date": "March 20, 2025",
        "title": "Translation Bureau to cut a quarter of its workforce over next 5 years",
        "publisher": "CBC News",
        "url": "https://www.cbc.ca/news/canada/ottawa/translation-bureau-to-cut-a-quarter-of-its-workforce-over-next-5-years-1.7488601?cmp=rss"
      }
    ],
    "id": 75
  },
  {
    "topic": "economy",
    "party": "Liberal",
    "title": {
      "EN": "Abandon consumer carbon levy"
    },
    "references": [
      {
        "date": "March 20, 2025",
        "title": "Donald Trump has changed the election game plan for Mark Carney and Pierre Poilievre. Here’s how",
        "publisher": "The Star",
        "url": "https://www.thestar.com/politics/federal/donald-trump-has-changed-the-election-game-plan-for-mark-carney-and-pierre-poilievre-here/article_2509d69c-6ecf-4d63-b47a-06789c818623.html"
      }
    ],
    "id": 76
  },
  {
    "topic": "economy",
    "party": "Liberal",
    "title": {
      "EN": "Eliminate capital gains tax expansion"
    },
    "references": [
      {
        "date": "March 20, 2025",
        "title": "Donald Trump has changed the election game plan for Mark Carney and Pierre Poilievre. Here’s how",
        "publisher": "The Star",
        "url": "https://www.thestar.com/politics/federal/donald-trump-has-changed-the-election-game-plan-for-mark-carney-and-pierre-poilievre-here/article_2509d69c-6ecf-4d63-b47a-06789c818623.html"
      }
    ],
    "id": 77
  },
  {
    "topic": "foreign-policy",
    "party": "Liberal",
    "title": {
      "EN": "Provide humanitarian aid to Palestinians in Gaza and West Bank"
    },
    "references": [
      {
        "date": "March 20, 2025",
        "title": "Canada pledges nearly $100M for Palestinians in Gaza, West Bank",
        "publisher": "The Star",
        "url": "https://www.thestar.com/politics/federal/canada-pledges-nearly-100m-for-palestinians-in-gaza-west-bank/article_274b104b-f99d-53e2-bd6f-4933c9fbe8b5.html"
      }
    ],
    "id": 78
  },
  {
    "topic": "international-trade",
    "party": "Liberal",
    "title": {
      "EN": "Strengthen trade and security alliances with France and UK"
    },
    "references": [
      {
        "date": "March 20, 2025",
        "title": "Prime Minister Mark Carney expected to call a federal election on Sunday",
        "publisher": "The Star",
        "url": "https://www.thestar.com/politics/federal-elections/prime-minister-mark-carney-expected-to-call-a-federal-election-on-sunday/article_43178843-2f45-50cd-895c-0306d87567e2.html"
      }
    ],
    "id": 79
  },
  {
    "topic": "foreign-policy",
    "party": "Liberal",
    "title": {
      "EN": "Shift security alliances towards Europe"
    },
    "references": [
      {
        "date": "March 19, 2025",
        "title": "Mark Carney looking to Europe to boost Canada’s security in shift away from reliance on U.S., sources say",
        "publisher": "The Star",
        "url": "https://www.thestar.com/politics/mark-carney-looking-to-europe-to-boost-canada-s-security-in-shift-away-from-reliance/article_8a871782-f454-4e7f-b8ca-b9b6d3e7b34f.html"
      }
    ],
    "id": 80
  },
  {
    "topic": "education",
    "party": "Conservative",
    "title": {
      "EN": "Reinstate $4,000 apprenticeship grants for licensed trades"
    },
    "references": [
      {
        "date": "March 21, 2025",
        "title": "Conservatives to Bring Back ‘More Boots, Less Suits,’ To Train 350,000 Trades workers",
        "publisher": "Conservative Party of Canada",
        "url": "https://www.conservative.ca/conservatives-to-bring-back-more-boots-less-suits-to-train-350000-trades-workers/#utm_source=rss&utm_medium=rss&utm_campaign=conservatives-to-bring-back-more-boots-less-suits-to-train-350000-trades-workers"
      }
    ],
    "id": 83
  },
  {
    "topic": "education",
    "party": "Conservative",
    "title": {
      "EN": "Fund training halls to skill up 350,000 young workers over 5 years"
    },
    "references": [
      {
        "date": "March 21, 2025",
        "title": "Conservatives to Bring Back ‘More Boots, Less Suits,’ To Train 350,000 Trades workers",
        "publisher": "Conservative Party of Canada",
        "url": "https://www.conservative.ca/conservatives-to-bring-back-more-boots-less-suits-to-train-350000-trades-workers/#utm_source=rss&utm_medium=rss&utm_campaign=conservatives-to-bring-back-more-boots-less-suits-to-train-350000-trades-workers"
      }
    ],
    "id": 84
  },
  {
    "topic": "social-assistance",
    "party": "Conservative",
    "title": {
      "EN": "Create rapid EI payouts for skilled tradespeople during training"
    },
    "references": [
      {
        "date": "March 21, 2025",
        "title": "Conservatives to Bring Back ‘More Boots, Less Suits,’ To Train 350,000 Trades workers",
        "publisher": "Conservative Party of Canada",
        "url": "https://www.conservative.ca/conservatives-to-bring-back-more-boots-less-suits-to-train-350000-trades-workers/#utm_source=rss&utm_medium=rss&utm_campaign=conservatives-to-bring-back-more-boots-less-suits-to-train-350000-trades-workers"
      }
    ],
    "id": 85
  },
  {
    "topic": "health-and-safety",
    "party": "Conservative",
    "title": {
      "EN": "Unify health and safety regulations for tradespeople across Canada"
    },
    "references": [
      {
        "date": "March 21, 2025",
        "title": "Conservatives to Bring Back ‘More Boots, Less Suits,’ To Train 350,000 Trades workers",
        "publisher": "Conservative Party of Canada",
        "url": "https://www.conservative.ca/conservatives-to-bring-back-more-boots-less-suits-to-train-350000-trades-workers/#utm_source=rss&utm_medium=rss&utm_campaign=conservatives-to-bring-back-more-boots-less-suits-to-train-350000-trades-workers"
      }
    ],
    "id": 86
  },
  {
    "topic": "environment",
    "party": "Conservative",
    "title": {
      "EN": "Repeal Impact Assessment Act, Oil Tanker Moratorium Act, and oil/gas production cap"
    },
    "references": [
      {
        "url": "https://www.conservative.ca/just-the-facts-mark-carney-opposes-energy-export-projects/#utm_source=rss&utm_medium=rss&utm_campaign=just-the-facts-mark-carney-opposes-energy-export-projects"
      }
    ],
    "id": 89
  },
  {
    "topic": "government",
    "party": "Conservative",
    "title": {
      "EN": "Re-establish a Ministry of Labour"
    },
    "references": [
      {
        "url": "https://www.conservative.ca/mark-carney-union-buster/#utm_source=rss&utm_medium=rss&utm_campaign=mark-carney-union-buster"
      }
    ],
    "id": 90
  },
  {
    "topic": "environment",
    "party": "Bloc",
    "title": {
      "EN": "Invest in infrastructure adaptation and greenhouse gas emissions reduction"
    },
    "references": [
      {
        "url": "https://www.blocquebecois.org/rapport-de-lirec-sur-limpact-des-changements-climatiques-linaction-climatique-a-un-cout/"
      }
    ],
    "id": 91
  },
  {
    "topic": "economy",
    "party": "NDP",
    "title": {
      "EN": "Oppose changes to capital gains inclusion rate"
    },
    "references": [
      {
        "url": "https://www.ndp.ca/news/ndp-react-carney-scrapping-capital-gains-tax"
      }
    ],
    "id": 92
  },
  {
    "topic": "environment",
    "party": "Liberal",
    "title": {
      "EN": "Maintain emissions cap on oil and gas production"
    },
    "references": [
      {
        "url": "https://www.conservative.ca/just-the-facts-mark-carney-opposes-energy-export-projects/#utm_source=rss&utm_medium=rss&utm_campaign=just-the-facts-mark-carney-opposes-energy-export-projects"
      }
    ],
    "id": 93
  },
  {
    "topic": "economy",
    "party": "Liberal",
    "title": {
      "EN": "Cancel capital gains tax increase, raise lifetime exemption"
    },
    "references": [
      {
        "url": "https://www.theglobeandmail.com/politics/federal-election/article-carney-confirms-liberals-will-drop-planned-capital-gains-tax-change/"
      },
      {
        "url": "https://www.cbc.ca/news/politics/carney-cancels-capital-gains-hike-1.7490020?cmp=rss"
      }
    ],
    "id": 94
  },
  {
    "topic": "health-and-safety",
    "party": "NDP",
    "title": {
      "EN": "Support major social programs like dental and pharmacare"
    },
    "references": [
      {
        "url": "https://www.cbc.ca/news/politics/ndp-polling-election-2025-1.7489648?cmp=rss"
      }
    ],
    "id": 95
  },
  {
    "topic": "government",
    "party": "Green",
    "title": {
      "EN": "Seek electoral co-operation agreement with Liberals, NDP, Bloc"
    },
    "references": [
      {
        "url": "https://www.cbc.ca/news/politics/jonathan-pedneault-co-leader-green-party-election-campaign-1.7489822?cmp=rss"
      }
    ],
    "id": 96
  },
  {
    "topic": "economy",
    "party": "Conservative",
    "title": {
      "EN": "Scrap carbon pricing on large industrial emitters"
    },
    "references": [
      {
        "url": "https://www.cbc.ca/news/politics/poilievre-trades-training-union-apprenticeships-1.7489825?cmp=rss"
      }
    ],
    "id": 97
  },
  {
    "topic": "infrastructure",
    "party": "Liberal",
    "title": {
      "EN": "Expedite major projects by ending duplicative environmental assessments"
    },
    "references": [
      {
        "url": "https://www.thestar.com/politics/mark-carney-says-he-ll-slash-red-tape-to-expedite-major-projects-like-high-speed/article_6f389d37-f119-4c79-a495-1ce7a156befa.html"
      }
    ],
    "id": 98
  },
  {
    "topic": "international-trade",
    "party": "Liberal",
    "title": {
      "EN": "Eliminate interprovincial trade barriers to counter U.S. tariffs"
    },
    "references": [
      {
        "date": "March 21, 2025",
        "title": "PM Carney meeting with premiers today before expected Sunday election call",
        "publisher": "CBC News",
        "url": "https://www.cbc.ca/news/politics/carney-premiers-meeting-1.7489368?cmp=rss"
      },
      {
        "url": "https://www.thestar.com/politics/mark-carney-says-he-ll-slash-red-tape-to-expedite-major-projects-like-high-speed/article_6f389d37-f119-4c79-a495-1ce7a156befa.html"
      }
    ],
    "id": 99
  },
  {
    "topic": "social-assistance",
    "party": "Liberal",
    "title": {
      "EN": "Waive one-week wait for EI benefits for workers affected by U.S. tariffs"
    },
    "references": [
      {
        "url": "https://www.thestar.com/politics/mark-carney-says-he-ll-slash-red-tape-to-expedite-major-projects-like-high-speed/article_6f389d37-f119-4c79-a495-1ce7a156befa.html"
      }
    ],
    "id": 100
  },
  {
    "topic": "economy",
    "party": "Liberal",
    "title": {
      "EN": "Defer corporate income tax and GST/HST payments for businesses impacted by tariffs"
    },
    "references": [
      {
        "url": "https://www.thestar.com/politics/mark-carney-says-he-ll-slash-red-tape-to-expedite-major-projects-like-high-speed/article_6f389d37-f119-4c79-a495-1ce7a156befa.html"
      }
    ],
    "id": 101
  },
  {
    "topic": "infrastructure",
    "party": "Liberal",
    "title": {
      "EN": "Support high-speed rail from Toronto to Québec City with $3.9B funding"
    },
    "references": [
      {
        "url": "https://www.thestar.com/politics/federal/head-of-canadas-high-speed-rail-project-wants-it-to-run-into-downtown-toronto/article_a1764783-582f-4365-885c-74a80e5868f2.html"
      }
    ],
    "id": 102
  },
  {
    "topic": "foreign-policy",
    "party": "Liberal",
    "title": {
      "EN": "Ease sanctions on Syria for democratization and humanitarian aid"
    },
    "references": [
      {
        "url": "https://www.thestar.com/politics/federal/syrian-canadians-hopeful-as-ottawa-takes-initial-steps-but-urge-more-action/article_e5c23bca-e318-5c62-98ad-63bb5a8fc822.html"
      }
    ],
    "id": 103
  },
  {
    "topic": "infrastructure",
    "party": "NDP",
    "title": {
      "EN": "Oppose private sector involvement in high-speed rail project"
    },
    "references": [
      {
        "url": "https://www.thestar.com/politics/federal/head-of-canadas-high-speed-rail-project-wants-it-to-run-into-downtown-toronto/article_a1764783-582f-4365-885c-74a80e5868f2.html"
      }
    ],
    "id": 104
  }
]
